arSort/__init__.py
arSort-0.1.dist-info/METADATA
arSort-0.1.dist-info/WHEEL
arSort-0.1.dist-info/top_level.txt
arSort-0.1.dist-info/RECORD
