Metadata-Version: 2.1
Name: arSort
Version: 0.1
Summary: a library for lazy people who are too lazy to write their own sorting
Home-page: https://github.com/diarama-py/arSort
Author: program_py
Author-email: semenovsvatoslav19@gmail.com
Classifier: Programming Language :: Python :: 3
Classifier: License :: OSI Approved :: MIT License
Classifier: Operating System :: OS Independent
Requires-Python: >=3.6
